{"nodes": [{"id": "c_sean_personal_projects_coding_swoosh_readme_md", "label": "README.md", "file_type": "document", "source_file": "C:\\Sean\\Personal Projects\\Coding\\swoosh\\README.md", "source_location": "L1"}, {"id": "swoosh_readme_swoosh", "label": "Swoosh", "file_type": "document", "source_file": "C:\\Sean\\Personal Projects\\Coding\\swoosh\\README.md", "source_location": "L1"}, {"id": "swoosh_readme_stack", "label": "Stack", "file_type": "document", "source_file": "C:\\Sean\\Personal Projects\\Coding\\swoosh\\README.md", "source_location": "L5"}, {"id": "swoosh_readme_setup", "label": "Setup", "file_type": "document", "source_file": "C:\\Sean\\Personal Projects\\Coding\\swoosh\\README.md", "source_location": "L11"}, {"id": "swoosh_readme_supabase", "label": "Supabase", "file_type": "document", "source_file": "C:\\Sean\\Personal Projects\\Coding\\swoosh\\README.md", "source_location": "L22"}, {"id": "swoosh_readme_monzo_recommended_automatic_sync", "label": "Monzo (recommended \u2014 automatic sync)", "file_type": "document", "source_file": "C:\\Sean\\Personal Projects\\Coding\\swoosh\\README.md", "source_location": "L26"}, {"id": "swoosh_readme_other_banks_csv_manual", "label": "Other banks (CSV / manual)", "file_type": "document", "source_file": "C:\\Sean\\Personal Projects\\Coding\\swoosh\\README.md", "source_location": "L36"}, {"id": "swoosh_readme_enable_banking_optional_limited_uk_coverage", "label": "Enable Banking (optional \u2014 limited UK coverage)", "file_type": "document", "source_file": "C:\\Sean\\Personal Projects\\Coding\\swoosh\\README.md", "source_location": "L40"}, {"id": "swoosh_readme_features", "label": "Features", "file_type": "document", "source_file": "C:\\Sean\\Personal Projects\\Coding\\swoosh\\README.md", "source_location": "L44"}, {"id": "swoosh_readme_git_commits", "label": "Git commits", "file_type": "document", "source_file": "C:\\Sean\\Personal Projects\\Coding\\swoosh\\README.md", "source_location": "L52"}], "edges": [{"source": "c_sean_personal_projects_coding_swoosh_readme_md", "target": "swoosh_readme_swoosh", "relation": "contains", "confidence": "EXTRACTED", "source_file": "C:\\Sean\\Personal Projects\\Coding\\swoosh\\README.md", "source_location": "L1", "weight": 1.0}, {"source": "swoosh_readme_swoosh", "target": "swoosh_readme_stack", "relation": "contains", "confidence": "EXTRACTED", "source_file": "C:\\Sean\\Personal Projects\\Coding\\swoosh\\README.md", "source_location": "L5", "weight": 1.0}, {"source": "swoosh_readme_swoosh", "target": "swoosh_readme_setup", "relation": "contains", "confidence": "EXTRACTED", "source_file": "C:\\Sean\\Personal Projects\\Coding\\swoosh\\README.md", "source_location": "L11", "weight": 1.0}, {"source": "swoosh_readme_swoosh", "target": "swoosh_readme_supabase", "relation": "contains", "confidence": "EXTRACTED", "source_file": "C:\\Sean\\Personal Projects\\Coding\\swoosh\\README.md", "source_location": "L22", "weight": 1.0}, {"source": "swoosh_readme_supabase", "target": "swoosh_readme_monzo_recommended_automatic_sync", "relation": "contains", "confidence": "EXTRACTED", "source_file": "C:\\Sean\\Personal Projects\\Coding\\swoosh\\README.md", "source_location": "L26", "weight": 1.0}, {"source": "swoosh_readme_supabase", "target": "swoosh_readme_other_banks_csv_manual", "relation": "contains", "confidence": "EXTRACTED", "source_file": "C:\\Sean\\Personal Projects\\Coding\\swoosh\\README.md", "source_location": "L36", "weight": 1.0}, {"source": "swoosh_readme_supabase", "target": "swoosh_readme_enable_banking_optional_limited_uk_coverage", "relation": "contains", "confidence": "EXTRACTED", "source_file": "C:\\Sean\\Personal Projects\\Coding\\swoosh\\README.md", "source_location": "L40", "weight": 1.0}, {"source": "swoosh_readme_swoosh", "target": "swoosh_readme_features", "relation": "contains", "confidence": "EXTRACTED", "source_file": "C:\\Sean\\Personal Projects\\Coding\\swoosh\\README.md", "source_location": "L44", "weight": 1.0}, {"source": "swoosh_readme_swoosh", "target": "swoosh_readme_git_commits", "relation": "contains", "confidence": "EXTRACTED", "source_file": "C:\\Sean\\Personal Projects\\Coding\\swoosh\\README.md", "source_location": "L52", "weight": 1.0}], "input_tokens": 0, "output_tokens": 0}